[
  {
    "x1": 0,
    "x2": 600,
    "y1": 0,
    "y2": 120,
    "z1": 0,
    "z2": 50,
    "label": "Frame",
    "posUpDown": "",
    "elementType": "Frame",
    "additionalInfos": null
  },
  {
    "x1": 0,
    "x2": 600,
    "y1": 0,
    "y2": 120,
    "z1": 900,
    "z2": 950,
    "label": "Frame",
    "posUpDown": "",
    "elementType": "Frame",
    "additionalInfos": null
  },
  {
    "x1": 0,
    "x2": 50,
    "y1": 0,
    "y2": 120,
    "z1": 50,
    "z2": 900,
    "label": "Frame",
    "posUpDown": "",
    "elementType": "Frame",
    "additionalInfos": null
  },
  {
    "x1": 550,
    "x2": 600,
    "y1": 0,
    "y2": 120,
    "z1": 50,
    "z2": 900,
    "label": "Frame",
    "posUpDown": "",
    "elementType": "Frame",
    "additionalInfos": null
  },
  {
    "x1": 50,
    "x2": 550,
    "y1": 170,
    "y2": 1020,
    "z1": 0,
    "z2": 50,
    "label": "Operational",
    "posUpDown": "",
    "elementType": "Removable_2",
    "additionalInfos": null
  },
  {
    "x1": 50,
    "x2": 550,
    "y1": 170,
    "y2": 1020,
    "z1": 900,
    "z2": 950,
    "label": "Back",
    "posUpDown": "",
    "elementType": "Wall",
    "additionalInfos": null
  },
  {
    "x1": 50,
    "x2": 550,
    "y1": 120,
    "y2": 170,
    "z1": 50,
    "z2": 900,
    "label": "Down_Wall",
    "posUpDown": "",
    "elementType": "Wall",
    "additionalInfos": null
  },
  {
    "x1": 50,
    "x2": 550,
    "y1": 1020,
    "y2": 1070,
    "z1": 50,
    "z2": 900,
    "label": "Up",
    "posUpDown": "",
    "elementType": "Wall",
    "additionalInfos": null
  },
  {
    "x1": 2250,
    "x2": 4150,
    "y1": 0,
    "y2": 120,
    "z1": -250,
    "z2": -200,
    "label": "Frame",
    "posUpDown": "",
    "elementType": "Frame",
    "additionalInfos": null
  },
  {
    "x1": 2250,
    "x2": 4150,
    "y1": 0,
    "y2": 120,
    "z1": 900,
    "z2": 950,
    "label": "Frame",
    "posUpDown": "",
    "elementType": "Frame",
    "additionalInfos": null
  },
  {
    "x1": 2250,
    "x2": 2300,
    "y1": 0,
    "y2": 120,
    "z1": -200,
    "z2": 900,
    "label": "Frame",
    "posUpDown": "",
    "elementType": "Frame",
    "additionalInfos": null
  },
  {
    "x1": 4100,
    "x2": 4150,
    "y1": 0,
    "y2": 120,
    "z1": -200,
    "z2": 900,
    "label": "Frame",
    "posUpDown": "",
    "elementType": "Frame",
    "additionalInfos": null
  },
  {
    "x1": 3175,
    "x2": 3225,
    "y1": 0,
    "y2": 120,
    "z1": 50,
    "z2": 1150,
    "label": "Frame",
    "posUpDown": "",
    "elementType": "Frame",
    "additionalInfos": null
  },
  {
    "x1": 2300,
    "x2": 4100,
    "y1": 170,
    "y2": 1020,
    "z1": -250,
    "z2": -200,
    "label": "Operational",
    "posUpDown": "",
    "elementType": "Removable_2",
    "additionalInfos": null
  },
  {
    "x1": 2300,
    "x2": 3200,
    "y1": 170,
    "y2": 1020,
    "z1": 900,
    "z2": 950,
    "label": "Back",
    "posUpDown": "",
    "elementType": "Wall",
    "additionalInfos": null
  },
  {
    "x1": 3250,
    "x2": 4100,
    "y1": 170,
    "y2": 1020,
    "z1": 900,
    "z2": 950,
    "label": "Back",
    "posUpDown": "",
    "elementType": "Wall",
    "additionalInfos": null
  },
  {
    "x1": 2300,
    "x2": 4100,
    "y1": 120,
    "y2": 170,
    "z1": -200,
    "z2": 650,
    "label": "Down_Wall",
    "posUpDown": "",
    "elementType": "Wall",
    "additionalInfos": null
  },
  {
    "x1": 2300,
    "x2": 3200,
    "y1": 1020,
    "y2": 1070,
    "z1": -200,
    "z2": 650,
    "label": "Up",
    "posUpDown": "",
    "elementType": "Wall",
    "additionalInfos": null
  },
  {
    "x1": 3250,
    "x2": 4100,
    "y1": 1020,
    "y2": 1070,
    "z1": -200,
    "z2": 650,
    "label": "Up",
    "posUpDown": "",
    "elementType": "Wall",
    "additionalInfos": null
  },
  {
    "x1": 600,
    "x2": 1000,
    "y1": 0,
    "y2": 120,
    "z1": -170,
    "z2": -120,
    "label": "Frame",
    "posUpDown": "",
    "elementType": "Frame",
    "additionalInfos": null
  },
  {
    "x1": 600,
    "x2": 1000,
    "y1": 0,
    "y2": 120,
    "z1": 1070,
    "z2": 1120,
    "label": "Frame",
    "posUpDown": "",
    "elementType": "Frame",
    "additionalInfos": null
  },
  {
    "x1": 600,
    "x2": 650,
    "y1": 0,
    "y2": 120,
    "z1": -120,
    "z2": 1070,
    "label": "Frame",
    "posUpDown": "",
    "elementType": "Frame",
    "additionalInfos": null
  },
  {
    "x1": 950,
    "x2": 1000,
    "y1": 0,
    "y2": 120,
    "z1": -120,
    "z2": 1070,
    "label": "Frame",
    "posUpDown": "",
    "elementType": "Frame",
    "additionalInfos": null
  },
  {
    "x1": 650,
    "x2": 950,
    "y1": 170,
    "y2": 1020,
    "z1": -170,
    "z2": -120,
    "label": "Operational",
    "posUpDown": "",
    "elementType": "Removable_2",
    "additionalInfos": null
  },
  {
    "x1": 650,
    "x2": 950,
    "y1": 1070,
    "y2": 1920,
    "z1": -170,
    "z2": -120,
    "label": "Operational",
    "posUpDown": "",
    "elementType": "Removable_2",
    "additionalInfos": null
  },
  {
    "x1": 650,
    "x2": 950,
    "y1": 170,
    "y2": 1020,
    "z1": 1070,
    "z2": 1120,
    "label": "Back",
    "posUpDown": "",
    "elementType": "Wall",
    "additionalInfos": null
  },
  {
    "x1": 650,
    "x2": 950,
    "y1": 1070,
    "y2": 1920,
    "z1": 1070,
    "z2": 1120,
    "label": "Back",
    "posUpDown": "",
    "elementType": "Wall",
    "additionalInfos": null
  },
  {
    "x1": 650,
    "x2": 950,
    "y1": 120,
    "y2": 170,
    "z1": -120,
    "z2": 1070,
    "label": "Down_Wall",
    "posUpDown": "",
    "elementType": "Wall",
    "additionalInfos": null
  },
  {
    "x1": 650,
    "x2": 950,
    "y1": 1920,
    "y2": 1870,
    "z1": -120,
    "z2": 1070,
    "label": "Up",
    "posUpDown": "",
    "elementType": "Wall",
    "additionalInfos": null
  },
  {
    "x1": 600,
    "x2": 650,
    "y1": 170,
    "y2": 1020,
    "z1": 975,
    "z2": 1070,
    "label": "FrontLeft",
    "posUpDown": "",
    "elementType": "Wall",
    "additionalInfos": null
  },
  {
    "x1": 600,
    "x2": 650,
    "y1": 170,
    "y2": 1020,
    "z1": -120,
    "z2": -25,
    "label": "FrontLeft",
    "posUpDown": "",
    "elementType": "Wall",
    "additionalInfos": null
  },
  {
    "x1": 600,
    "x2": 650,
    "y1": 1070,
    "y2": 1920,
    "z1": 975,
    "z2": 1070,
    "label": "FrontLeft",
    "posUpDown": "",
    "elementType": "Wall",
    "additionalInfos": null
  },
  {
    "x1": 600,
    "x2": 650,
    "y1": 1070,
    "y2": 1920,
    "z1": -120,
    "z2": -25,
    "label": "FrontLeft",
    "posUpDown": "",
    "elementType": "Wall",
    "additionalInfos": null
  },
  {
    "x1": 1000,
    "x2": 1050,
    "y1": 170,
    "y2": 1020,
    "z1": 975,
    "z2": 1070,
    "label": "FrontRight",
    "posUpDown": "",
    "elementType": "Wall",
    "additionalInfos": null
  },
  {
    "x1": 1000,
    "x2": 1050,
    "y1": 170,
    "y2": 1020,
    "z1": -120,
    "z2": -25,
    "label": "FrontRight",
    "posUpDown": "",
    "elementType": "Wall",
    "additionalInfos": null
  },
  {
    "x1": 1000,
    "x2": 1050,
    "y1": 1070,
    "y2": 1920,
    "z1": 975,
    "z2": 1070,
    "label": "FrontRight",
    "posUpDown": "",
    "elementType": "Wall",
    "additionalInfos": null
  },
  {
    "x1": 1000,
    "x2": 1050,
    "y1": 1070,
    "y2": 1920,
    "z1": -120,
    "z2": -25,
    "label": "FrontRight",
    "posUpDown": "",
    "elementType": "Wall",
    "additionalInfos": null
  },
  {
    "x1": 1000,
    "x2": 2250,
    "y1": 0,
    "y2": 120,
    "z1": 0,
    "z2": 50,
    "label": "Frame",
    "posUpDown": "",
    "elementType": "Frame",
    "additionalInfos": null
  },
  {
    "x1": 1000,
    "x2": 2250,
    "y1": 0,
    "y2": 120,
    "z1": 900,
    "z2": 950,
    "label": "Frame",
    "posUpDown": "",
    "elementType": "Frame",
    "additionalInfos": null
  },
  {
    "x1": 1000,
    "x2": 1050,
    "y1": 0,
    "y2": 120,
    "z1": 50,
    "z2": 900,
    "label": "Frame",
    "posUpDown": "",
    "elementType": "Frame",
    "additionalInfos": null
  },
  {
    "x1": 2200,
    "x2": 2250,
    "y1": 0,
    "y2": 120,
    "z1": 50,
    "z2": 900,
    "label": "Frame",
    "posUpDown": "",
    "elementType": "Frame",
    "additionalInfos": null
  },
  {
    "x1": 1050,
    "x2": 1850,
    "y1": 1070,
    "y2": 1920,
    "z1": 0,
    "z2": 50,
    "label": "Operational",
    "posUpDown": "",
    "elementType": "Removable_2",
    "additionalInfos": null
  },
  {
    "x1": 1900,
    "x2": 2200,
    "y1": 1070,
    "y2": 1920,
    "z1": 0,
    "z2": 50,
    "label": "Operational",
    "posUpDown": "",
    "elementType": "Removable_2",
    "additionalInfos": null
  },
  {
    "x1": 1050,
    "x2": 1850,
    "y1": 170,
    "y2": 1020,
    "z1": 0,
    "z2": 50,
    "label": "Operational",
    "posUpDown": "",
    "elementType": "Removable_2",
    "additionalInfos": null
  },
  {
    "x1": 1900,
    "x2": 2200,
    "y1": 170,
    "y2": 1020,
    "z1": 0,
    "z2": 50,
    "label": "Operational",
    "posUpDown": "",
    "elementType": "Removable_2",
    "additionalInfos": null
  },
  {
    "x1": 1050,
    "x2": 2200,
    "y1": 1070,
    "y2": 1920,
    "z1": 900,
    "z2": 950,
    "label": "Back",
    "posUpDown": "",
    "elementType": "Wall",
    "additionalInfos": null
  },
  {
    "x1": 1050,
    "x2": 2200,
    "y1": 170,
    "y2": 1020,
    "z1": 900,
    "z2": 950,
    "label": "Back",
    "posUpDown": "",
    "elementType": "Wall",
    "additionalInfos": null
  },
  {
    "x1": 1050,
    "x2": 2200,
    "y1": 120,
    "y2": 170,
    "z1": 50,
    "z2": 900,
    "label": "Down_Wall",
    "posUpDown": "",
    "elementType": "Wall",
    "additionalInfos": null
  },
  {
    "x1": 1050,
    "x2": 2200,
    "y1": 1070,
    "y2": 1120,
    "z1": 50,
    "z2": 900,
    "label": "Middle_Wall",
    "posUpDown": "",
    "elementType": "Wall",
    "additionalInfos": null
  },
  {
    "x1": 1050,
    "x2": 2200,
    "y1": 1920,
    "y2": 1970,
    "z1": 50,
    "z2": 900,
    "label": "Up",
    "posUpDown": "",
    "elementType": "Wall",
    "additionalInfos": null
  },
  {
    "x1": 2050,
    "x2": 2090,
    "y1": 170,
    "y2": 210,
    "z1": 0,
    "z2": -150,
    "label": "Connector",
    "posUpDown": "DrainTray: AhuEmptySectionOutput / Up: 0, Down: 4",
    "elementType": null,
    "additionalInfos": null
  },
  {
    "x1": 10,
    "x2": 590,
    "y1": 130,
    "y2": 1060,
    "z1": 10,
    "z2": 940,
    "label": "Block",
    "posUpDown": "Block: Up 0, Down 1",
    "elementType": null,
    "additionalInfos": {
      "sName": null,
      "airPath": null,
      "iconPosition": null,
      "iconName": null,
      "positionUp": 0,
      "positionDown": 0,
      "blockNumber": 1
    }
  },
  {
    "x1": 610,
    "x2": 990,
    "y1": 130,
    "y2": 1960,
    "z1": -160,
    "z2": 1110,
    "label": "Block",
    "posUpDown": "Block: Up 1, Down 2",
    "elementType": null,
    "additionalInfos": {
      "sName": null,
      "airPath": null,
      "iconPosition": null,
      "iconName": null,
      "positionUp": 0,
      "positionDown": 0,
      "blockNumber": 2
    }
  },
  {
    "x1": 1010,
    "x2": 2240,
    "y1": 130,
    "y2": 1960,
    "z1": 10,
    "z2": 940,
    "label": "Block",
    "posUpDown": "Block: Up 2, Down 3",
    "elementType": null,
    "additionalInfos": {
      "sName": null,
      "airPath": null,
      "iconPosition": null,
      "iconName": null,
      "positionUp": 0,
      "positionDown": 0,
      "blockNumber": 3
    }
  },
  {
    "x1": 2260,
    "x2": 4140,
    "y1": 130,
    "y2": 1060,
    "z1": -240,
    "z2": 940,
    "label": "Block",
    "posUpDown": "Block: Up 0, Down 4",
    "elementType": null,
    "additionalInfos": {
      "sName": null,
      "airPath": null,
      "iconPosition": null,
      "iconName": null,
      "positionUp": 0,
      "positionDown": 0,
      "blockNumber": 4
    }
  },
  {
    "x1": 0,
    "x2": 5,
    "y1": 170,
    "y2": 1020,
    "z1": 50,
    "z2": 900,
    "label": "Hole",
    "posUpDown": "",
    "elementType": null,
    "additionalInfos": null
  },
  {
    "x1": 4150,
    "x2": 4155,
    "y1": 170,
    "y2": 1020,
    "z1": -75,
    "z2": 775,
    "label": "Hole",
    "posUpDown": "",
    "elementType": null,
    "additionalInfos": null
  },
  {
    "x1": 2250,
    "x2": 2255,
    "y1": 1070,
    "y2": 1920,
    "z1": 50,
    "z2": 900,
    "label": "Hole",
    "posUpDown": "",
    "elementType": null,
    "additionalInfos": null
  },
  {
    "x1": 600,
    "x2": 605,
    "y1": 1070,
    "y2": 1920,
    "z1": 50,
    "z2": 900,
    "label": "Hole",
    "posUpDown": "",
    "elementType": null,
    "additionalInfos": null
  },
  {
    "x1": -115,
    "x2": 0,
    "y1": 180,
    "y2": 1010,
    "z1": 50,
    "z2": 900,
    "label": "AD",
    "posUpDown": "",
    "elementType": null,
    "additionalInfos": null
  },
  {
    "x1": 485,
    "x2": 600,
    "y1": 1080,
    "y2": 1910,
    "z1": 50,
    "z2": 900,
    "label": "AD",
    "posUpDown": "",
    "elementType": null,
    "additionalInfos": null
  },
  {
    "x1": -215,
    "x2": -115,
    "y1": 180,
    "y2": 1000,
    "z1": 50,
    "z2": 900,
    "label": "FC",
    "posUpDown": "",
    "elementType": null,
    "additionalInfos": null
  },
  {
    "x1": 4155,
    "x2": 4255,
    "y1": 180,
    "y2": 1000,
    "z1": -75,
    "z2": 775,
    "label": "FC",
    "posUpDown": "",
    "elementType": null,
    "additionalInfos": null
  },
  {
    "x1": 2255,
    "x2": 2355,
    "y1": 1080,
    "y2": 1900,
    "z1": 50,
    "z2": 900,
    "label": "FC",
    "posUpDown": "",
    "elementType": null,
    "additionalInfos": null
  },
  {
    "x1": 385,
    "x2": 485,
    "y1": 1080,
    "y2": 1900,
    "z1": 50,
    "z2": 900,
    "label": "FC",
    "posUpDown": "",
    "elementType": null,
    "additionalInfos": null
  },
  {
    "x1": 50,
    "x2": 550,
    "y1": 170,
    "y2": 1020,
    "z1": 50,
    "z2": 900,
    "label": "Function",
    "posUpDown": "PF, U:0, D:1",
    "elementType": "Function",
    "additionalInfos": {
      "sName": "PF",
      "airPath": "Supply",
      "iconPosition": null,
      "iconName": null,
      "positionUp": 0,
      "positionDown": 0,
      "blockNumber": 0
    }
  },
  {
    "x1": 2300,
    "x2": 4100,
    "y1": 170,
    "y2": 1020,
    "z1": -200,
    "z2": 900,
    "label": "Function",
    "posUpDown": "GM, U:0, D:5",
    "elementType": "Function",
    "additionalInfos": {
      "sName": "GM",
      "airPath": "Supply",
      "iconPosition": null,
      "iconName": null,
      "positionUp": 0,
      "positionDown": 0,
      "blockNumber": 0
    }
  },
  {
    "x1": 650,
    "x2": 950,
    "y1": 170,
    "y2": 1920,
    "z1": -120,
    "z2": 1070,
    "label": "Function",
    "posUpDown": "RR, U:1, D:2",
    "elementType": "Function",
    "additionalInfos": {
      "sName": "RR",
      "airPath": "Supply",
      "iconPosition": null,
      "iconName": null,
      "positionUp": 0,
      "positionDown": 0,
      "blockNumber": 0
    }
  },
  {
    "x1": 1050,
    "x2": 1850,
    "y1": 170,
    "y2": 1020,
    "z1": 50,
    "z2": 900,
    "label": "Function",
    "posUpDown": "VF, U:0, D:3",
    "elementType": "Function",
    "additionalInfos": {
      "sName": "VF",
      "airPath": "Supply",
      "iconPosition": null,
      "iconName": null,
      "positionUp": 0,
      "positionDown": 0,
      "blockNumber": 0
    }
  },
  {
    "x1": 1900,
    "x2": 2200,
    "y1": 170,
    "y2": 1020,
    "z1": 50,
    "z2": 900,
    "label": "Function",
    "posUpDown": "ES, U:0, D:4",
    "elementType": "Function",
    "additionalInfos": {
      "sName": "ES",
      "airPath": "Supply",
      "iconPosition": null,
      "iconName": null,
      "positionUp": 0,
      "positionDown": 0,
      "blockNumber": 0
    }
  },
  {
    "x1": 1050,
    "x2": 1850,
    "y1": 1070,
    "y2": 1920,
    "z1": 50,
    "z2": 900,
    "label": "Function",
    "posUpDown": "VF, U:2, D:0",
    "elementType": "Function",
    "additionalInfos": {
      "sName": "VF",
      "airPath": "Exhaust",
      "iconPosition": null,
      "iconName": null,
      "positionUp": 0,
      "positionDown": 0,
      "blockNumber": 0
    }
  },
  {
    "x1": 1900,
    "x2": 2200,
    "y1": 1070,
    "y2": 1920,
    "z1": 50,
    "z2": 900,
    "label": "Function",
    "posUpDown": "PF, U:3, D:0",
    "elementType": "Function",
    "additionalInfos": {
      "sName": "PF",
      "airPath": "Exhaust",
      "iconPosition": null,
      "iconName": null,
      "positionUp": 0,
      "positionDown": 0,
      "blockNumber": 0
    }
  },
  {
    "x1": 250,
    "x2": 350,
    "y1": 703,
    "y2": 803,
    "z1": -1,
    "z2": -1,
    "label": "icon_filter",
    "posUpDown": "Icon: PF",
    "elementType": "Icon",
    "additionalInfos": {
      "sName": "PF",
      "airPath": "Supply",
      "iconPosition": "Operational",
      "iconName": "PF",
      "positionUp": 0,
      "positionDown": 0,
      "blockNumber": 0
    }
  },
  {
    "x1": 250,
    "x2": 350,
    "y1": 703,
    "y2": 803,
    "z1": 951,
    "z2": 951,
    "label": "icon_filter",
    "posUpDown": "Icon: PF",
    "elementType": "Icon",
    "additionalInfos": {
      "sName": "PF",
      "airPath": "Supply",
      "iconPosition": "Back",
      "iconName": "PF",
      "positionUp": 0,
      "positionDown": 0,
      "blockNumber": 0
    }
  },
  {
    "x1": 250,
    "x2": 350,
    "y1": 1071,
    "y2": 1071,
    "z1": 425,
    "z2": 525,
    "label": "icon_filter",
    "posUpDown": "Icon: PF",
    "elementType": "Icon",
    "additionalInfos": {
      "sName": "PF",
      "airPath": "Supply",
      "iconPosition": "Up",
      "iconName": "PF",
      "positionUp": 0,
      "positionDown": 0,
      "blockNumber": 0
    }
  },
  {
    "x1": 3150,
    "x2": 3250,
    "y1": 703,
    "y2": 803,
    "z1": -251,
    "z2": -251,
    "label": "icon_gas",
    "posUpDown": "Icon: GM",
    "elementType": "Icon",
    "additionalInfos": {
      "sName": "GM",
      "airPath": "Supply",
      "iconPosition": "Operational",
      "iconName": "GM",
      "positionUp": 0,
      "positionDown": 0,
      "blockNumber": 0
    }
  },
  {
    "x1": 3150,
    "x2": 3250,
    "y1": 703,
    "y2": 803,
    "z1": 951,
    "z2": 951,
    "label": "icon_gas",
    "posUpDown": "Icon: GM",
    "elementType": "Icon",
    "additionalInfos": {
      "sName": "GM",
      "airPath": "Supply",
      "iconPosition": "Back",
      "iconName": "GM",
      "positionUp": 0,
      "positionDown": 0,
      "blockNumber": 0
    }
  },
  {
    "x1": 3150,
    "x2": 3250,
    "y1": 1071,
    "y2": 1071,
    "z1": 300,
    "z2": 400,
    "label": "icon_gas",
    "posUpDown": "Icon: GM",
    "elementType": "Icon",
    "additionalInfos": {
      "sName": "GM",
      "airPath": "Supply",
      "iconPosition": "Up",
      "iconName": "GM",
      "positionUp": 0,
      "positionDown": 0,
      "blockNumber": 0
    }
  },
  {
    "x1": 750,
    "x2": 850,
    "y1": 995,
    "y2": 1095,
    "z1": -171,
    "z2": -171,
    "label": "icon_rotor",
    "posUpDown": "Icon: RR",
    "elementType": "Icon",
    "additionalInfos": {
      "sName": "RR",
      "airPath": "Supply",
      "iconPosition": "Operational",
      "iconName": "RR",
      "positionUp": 0,
      "positionDown": 0,
      "blockNumber": 0
    }
  },
  {
    "x1": 750,
    "x2": 850,
    "y1": 995,
    "y2": 1095,
    "z1": 1121,
    "z2": 1121,
    "label": "icon_rotor",
    "posUpDown": "Icon: RR",
    "elementType": "Icon",
    "additionalInfos": {
      "sName": "RR",
      "airPath": "Supply",
      "iconPosition": "Back",
      "iconName": "RR",
      "positionUp": 0,
      "positionDown": 0,
      "blockNumber": 0
    }
  },
  {
    "x1": 750,
    "x2": 850,
    "y1": 1971,
    "y2": 1971,
    "z1": 425,
    "z2": 525,
    "label": "icon_rotor",
    "posUpDown": "Icon: RR",
    "elementType": "Icon",
    "additionalInfos": {
      "sName": "RR",
      "airPath": "Supply",
      "iconPosition": "Up",
      "iconName": "RR",
      "positionUp": 0,
      "positionDown": 0,
      "blockNumber": 0
    }
  },
  {
    "x1": 1400,
    "x2": 1500,
    "y1": 703,
    "y2": 803,
    "z1": -1,
    "z2": -1,
    "label": "icon_fan",
    "posUpDown": "Icon: VF",
    "elementType": "Icon",
    "additionalInfos": {
      "sName": "VF",
      "airPath": "Supply",
      "iconPosition": "Operational",
      "iconName": "VF",
      "positionUp": 0,
      "positionDown": 0,
      "blockNumber": 0
    }
  },
  {
    "x1": 1400,
    "x2": 1500,
    "y1": 703,
    "y2": 803,
    "z1": 951,
    "z2": 951,
    "label": "icon_fan",
    "posUpDown": "Icon: VF",
    "elementType": "Icon",
    "additionalInfos": {
      "sName": "VF",
      "airPath": "Supply",
      "iconPosition": "Back",
      "iconName": "VF",
      "positionUp": 0,
      "positionDown": 0,
      "blockNumber": 0
    }
  },
  {
    "x1": 1400,
    "x2": 1500,
    "y1": 1071,
    "y2": 1071,
    "z1": 425,
    "z2": 525,
    "label": "icon_fan",
    "posUpDown": "Icon: VF",
    "elementType": "Icon",
    "additionalInfos": {
      "sName": "VF",
      "airPath": "Supply",
      "iconPosition": "Up",
      "iconName": "VF",
      "positionUp": 0,
      "positionDown": 0,
      "blockNumber": 0
    }
  },
  {
    "x1": 2000,
    "x2": 2100,
    "y1": 703,
    "y2": 803,
    "z1": -1,
    "z2": -1,
    "label": "icon_emptysection",
    "posUpDown": "Icon: ES",
    "elementType": "Icon",
    "additionalInfos": {
      "sName": "ES",
      "airPath": "Supply",
      "iconPosition": "Operational",
      "iconName": "ES",
      "positionUp": 0,
      "positionDown": 0,
      "blockNumber": 0
    }
  },
  {
    "x1": 2000,
    "x2": 2100,
    "y1": 703,
    "y2": 803,
    "z1": 951,
    "z2": 951,
    "label": "icon_emptysection",
    "posUpDown": "Icon: ES",
    "elementType": "Icon",
    "additionalInfos": {
      "sName": "ES",
      "airPath": "Supply",
      "iconPosition": "Back",
      "iconName": "ES",
      "positionUp": 0,
      "positionDown": 0,
      "blockNumber": 0
    }
  },
  {
    "x1": 2000,
    "x2": 2100,
    "y1": 1071,
    "y2": 1071,
    "z1": 425,
    "z2": 525,
    "label": "icon_emptysection",
    "posUpDown": "Icon: ES",
    "elementType": "Icon",
    "additionalInfos": {
      "sName": "ES",
      "airPath": "Supply",
      "iconPosition": "Up",
      "iconName": "ES",
      "positionUp": 0,
      "positionDown": 0,
      "blockNumber": 0
    }
  },
  {
    "x1": 1400,
    "x2": 1500,
    "y1": 1287,
    "y2": 1387,
    "z1": -1,
    "z2": -1,
    "label": "icon_fan",
    "posUpDown": "Icon: VF",
    "elementType": "Icon",
    "additionalInfos": {
      "sName": "VF",
      "airPath": "Exhaust",
      "iconPosition": "Operational",
      "iconName": "VF",
      "positionUp": 0,
      "positionDown": 0,
      "blockNumber": 0
    }
  },
  {
    "x1": 1400,
    "x2": 1500,
    "y1": 1287,
    "y2": 1387,
    "z1": 951,
    "z2": 951,
    "label": "icon_fan",
    "posUpDown": "Icon: VF",
    "elementType": "Icon",
    "additionalInfos": {
      "sName": "VF",
      "airPath": "Exhaust",
      "iconPosition": "Back",
      "iconName": "VF",
      "positionUp": 0,
      "positionDown": 0,
      "blockNumber": 0
    }
  },
  {
    "x1": 1400,
    "x2": 1500,
    "y1": 1971,
    "y2": 1971,
    "z1": 425,
    "z2": 525,
    "label": "icon_fan",
    "posUpDown": "Icon: VF",
    "elementType": "Icon",
    "additionalInfos": {
      "sName": "VF",
      "airPath": "Exhaust",
      "iconPosition": "Up",
      "iconName": "VF",
      "positionUp": 0,
      "positionDown": 0,
      "blockNumber": 0
    }
  },
  {
    "x1": 2000,
    "x2": 2100,
    "y1": 1287,
    "y2": 1387,
    "z1": -1,
    "z2": -1,
    "label": "icon_filter",
    "posUpDown": "Icon: PF",
    "elementType": "Icon",
    "additionalInfos": {
      "sName": "PF",
      "airPath": "Exhaust",
      "iconPosition": "Operational",
      "iconName": "PF",
      "positionUp": 0,
      "positionDown": 0,
      "blockNumber": 0
    }
  },
  {
    "x1": 2000,
    "x2": 2100,
    "y1": 1287,
    "y2": 1387,
    "z1": 951,
    "z2": 951,
    "label": "icon_filter",
    "posUpDown": "Icon: PF",
    "elementType": "Icon",
    "additionalInfos": {
      "sName": "PF",
      "airPath": "Exhaust",
      "iconPosition": "Back",
      "iconName": "PF",
      "positionUp": 0,
      "positionDown": 0,
      "blockNumber": 0
    }
  },
  {
    "x1": 2000,
    "x2": 2100,
    "y1": 1971,
    "y2": 1971,
    "z1": 425,
    "z2": 525,
    "label": "icon_filter",
    "posUpDown": "Icon: PF",
    "elementType": "Icon",
    "additionalInfos": {
      "sName": "PF",
      "airPath": "Exhaust",
      "iconPosition": "Up",
      "iconName": "PF",
      "positionUp": 0,
      "positionDown": 0,
      "blockNumber": 0
    }
  }
]